[{"id":"cc3d523f8ffe7d582f7d98718b83347c","sport_key":"basketball_wncaab","sport_title":"WNCAAB","commence_time":"2026-03-05T16:00:00Z","home_team":"Virginia Cavaliers","away_team":"Clemson Tigers","bookmakers":[{"key":"draftkings","title":"DraftKings","last_update":"2026-03-05T14:12:39Z","markets":[{"key":"h2h","last_update":"2026-03-05T14:12:39Z","outcomes":[{"name":"Clemson Tigers","price":124},{"name":"Virginia Cavaliers","price":-148}]}]},{"key":"betrivers","title":"BetRivers","last_update":"2026-03-05T14:13:12Z","markets":[{"key":"h2h","last_update":"2026-03-05T14:13:12Z","outcomes":[{"name":"Clemson Tigers","price":112},{"name":"Virginia Cavaliers","price":-148}]}]}]},{"id":"ccb2c5929d6db59dc5b241562f8f4fe9","sport_key":"basketball_wncaab","sport_title":"WNCAAB","commence_time":"2026-03-05T16:00:00Z","home_team":"Georgia Bulldogs","away_team":"Kentucky Wildcats","bookmakers":[{"key":"betrivers","title":"BetRivers","last_update":"2026-03-05T14:13:12Z","markets":[{"key":"h2h","last_update":"2026-03-05T14:13:12Z","outcomes":[{"name":"Georgia Bulldogs","price":180},{"name":"Kentucky Wildcats","price":-250}]}]},{"key":"draftkings","title":"DraftKings","last_update":"2026-03-05T14:12:39Z","markets":[{"key":"h2h","last_update":"2026-03-05T14:12:39Z","outcomes":[{"name":"Georgia Bulldogs","price":230},{"name":"Kentucky Wildcats","price":-285}]}]}]},{"id":"b9d56050cf69572590d4f5fa20a5e608","sport_key":"basketball_wncaab","sport_title":"WNCAAB","commence_time":"2026-03-05T18:30:00Z","home_team":"Oklahoma Sooners","away_team":"Florida Gators","bookmakers":[{"key":"betrivers","title":"BetRivers","last_update":"2026-03-05T14:13:12Z","markets":[{"key":"h2h","last_update":"2026-03-05T14:13:12Z","outcomes":[{"name":"Florida Gators","price":390},{"name":"Oklahoma Sooners","price":-670}]}]},{"key":"draftkings","title":"DraftKings","last_update":"2026-03-05T14:12:39Z","markets":[{"key":"h2h","last_update":"2026-03-05T14:12:39Z","outcomes":[{"name":"Florida Gators","price":550},{"name":"Oklahoma Sooners","price":-800}]}]}]},{"id":"5ddb7629d8763e4f92c3dec093b1449d","sport_key":"basketball_wncaab","sport_title":"WNCAAB","commence_time":"2026-03-05T18:30:00Z","home_team":"Notre Dame Fighting Irish","away_team":"Miami Hurricanes","bookmakers":[{"key":"draftkings","title":"DraftKings","last_update":"2026-03-05T14:12:39Z","markets":[{"key":"h2h","last_update":"2026-03-05T14:12:39Z","outcomes":[{"name":"Miami Hurricanes","price":455},{"name":"Notre Dame Fighting Irish","price":-625}]}]}]}]
