[{"id":"0af64b1a1cbfed5a6f8e5c7468fb2eb8","sport_key":"basketball_wncaab","sport_title":"WNCAAB","commence_time":"2026-03-11T19:20:00Z","home_team":"Ball State Cardinals","away_team":"Bowling Green Falcons","bookmakers":[]},{"id":"f0e54aa0e31afe75de088161e566ae23","sport_key":"basketball_wncaab","sport_title":"WNCAAB","commence_time":"2026-03-11T21:03:35Z","home_team":"Idaho Vandals","away_team":"Montana St Bobcats","bookmakers":[{"key":"draftkings","title":"DraftKings","last_update":"2026-03-11T22:16:00Z","markets":[{"key":"h2h","last_update":"2026-03-11T22:16:00Z","outcomes":[{"name":"Idaho Vandals","price":-298},{"name":"Montana St Bobcats","price":220}]}]},{"key":"betrivers","title":"BetRivers","last_update":"2026-03-11T22:15:52Z","markets":[{"key":"h2h","last_update":"2026-03-11T22:15:52Z","outcomes":[{"name":"Idaho Vandals","price":-435},{"name":"Montana St Bobcats","price":260}]}]},{"key":"betmgm","title":"BetMGM","last_update":"2026-03-11T22:15:37Z","markets":[{"key":"h2h","last_update":"2026-03-11T22:15:37Z","outcomes":[{"name":"Idaho Vandals","price":-275},{"name":"Montana St Bobcats","price":210}]}]},{"key":"fanduel","title":"FanDuel","last_update":"2026-03-11T22:16:08Z","markets":[{"key":"h2h","last_update":"2026-03-11T22:16:08Z","outcomes":[{"name":"Idaho Vandals","price":-440},{"name":"Montana St Bobcats","price":290}]}]}]},{"id":"fab504827288d67ed24950abd67708e6","sport_key":"basketball_wncaab","sport_title":"WNCAAB","commence_time":"2026-03-11T21:42:00Z","home_team":"UC Santa Barbara Gauchos","away_team":"UC Riverside Highlanders","bookmakers":[{"key":"betrivers","title":"BetRivers","last_update":"2026-03-11T22:15:52Z","markets":[{"key":"h2h","last_update":"2026-03-11T22:15:52Z","outcomes":[{"name":"UC Riverside Highlanders","price":155},{"name":"UC Santa Barbara Gauchos","price":-230}]}]},{"key":"fanduel","title":"FanDuel","last_update":"2026-03-11T22:16:08Z","markets":[{"key":"h2h","last_update":"2026-03-11T22:16:08Z","outcomes":[{"name":"UC Riverside Highlanders","price":108},{"name":"UC Santa Barbara Gauchos","price":-144}]}]},{"key":"betmgm","title":"BetMGM","last_update":"2026-03-11T22:15:37Z","markets":[{"key":"h2h","last_update":"2026-03-11T22:15:37Z","outcomes":[{"name":"UC Riverside Highlanders","price":110},{"name":"UC Santa Barbara Gauchos","price":-145}]}]}]},{"id":"d776e91e6e141ea21a113b9a49cee91e","sport_key":"basketball_wncaab","sport_title":"WNCAAB","commence_time":"2026-03-11T22:03:11Z","home_team":"UT-Arlington Mavericks","away_team":"Utah Tech Trailblazers","bookmakers":[{"key":"draftkings","title":"DraftKings","last_update":"2026-03-11T22:16:00Z","markets":[{"key":"h2h","last_update":"2026-03-11T22:16:00Z","outcomes":[{"name":"UT-Arlington Mavericks","price":-166},{"name":"Utah Tech Trailblazers","price":130}]}]},{"key":"betmgm","title":"BetMGM","last_update":"2026-03-11T22:15:37Z","markets":[{"key":"h2h","last_update":"2026-03-11T22:15:37Z","outcomes":[{"name":"UT-Arlington Mavericks","price":-135},{"name":"Utah Tech Trailblazers","price":105}]}]},{"key":"fanduel","title":"FanDuel","last_update":"2026-03-11T22:16:08Z","markets":[{"key":"h2h","last_update":"2026-03-11T22:16:08Z","outcomes":[{"name":"UT-Arlington Mavericks","price":-192},{"name":"Utah Tech Trailblazers","price":142}]}]}]},{"id":"ce8ead15dcf94e1b5fbaa4cc273b3f48","sport_key":"basketball_wncaab","sport_title":"WNCAAB","commence_time":"2026-03-11T22:20:00Z","home_team":"Massachusetts Minutewomen","away_team":"Toledo Rockets","bookmakers":[{"key":"betrivers","title":"BetRivers","last_update":"2026-03-11T22:15:52Z","markets":[{"key":"h2h","last_update":"2026-03-11T22:15:52Z","outcomes":[{"name":"Massachusetts Minutewomen","price":-265},{"name":"Toledo Rockets","price":190}]}]},{"key":"fanduel","title":"FanDuel","last_update":"2026-03-11T22:16:08Z","markets":[{"key":"h2h","last_update":"2026-03-11T22:16:08Z","outcomes":[{"name":"Massachusetts Minutewomen","price":-245},{"name":"Toledo Rockets","price":178}]}]},{"key":"betmgm","title":"BetMGM","last_update":"2026-03-11T22:15:37Z","markets":[{"key":"h2h","last_update":"2026-03-11T22:15:37Z","outcomes":[{"name":"Massachusetts Minutewomen","price":-250},{"name":"Toledo Rockets","price":200}]}]}]}]
